autodiffcst/.DS_Store
autodiffcst/AD.py
autodiffcst/AD_vec.py
autodiffcst/__init__.py
autodiffcst/admath.py
autodiffcst/__pycache__/AD.cpython-37.pyc
autodiffcst/__pycache__/AD_vec.cpython-37.pyc
autodiffcst/__pycache__/__init__.cpython-37.pyc
autodiffcst/__pycache__/admath.cpython-37.pyc
autodiffcst/__pycache__/skeleton.cpython-37.pyc
autodiffcst/__pycache__/trigmath.cpython-37.pyc
autodiffCST-0.0.4.dist-info/AUTHORS.rst
autodiffCST-0.0.4.dist-info/LICENSE.txt
autodiffCST-0.0.4.dist-info/METADATA
autodiffCST-0.0.4.dist-info/WHEEL
autodiffCST-0.0.4.dist-info/top_level.txt
autodiffCST-0.0.4.dist-info/RECORD
