Metadata-Version: 2.1
Name: autodiffCST
Version: 0.0.4
Summary: This package autodiffCST implements automatic differentiation. Users could perform forward mode, and use it for higher order differentiation.
Home-page: https://github.com/auto-differentiaters-in-CST/cs107-FinalProject
Author: Xiaohan Yang, Hanwen Zhang, Runting Yang, Max Li
Author-email: xiaohan_yang@g.harvard.edu, hzhang1@g.harvard.edu, runting_yang@hsph.harvard.edu, manli@fas.harvard.edu
License: mit
Project-URL: Documentation, https://github.com/auto-differentiaters-in-CST/cs107-FinalProject/blob/master/docs/documentation.ipynb
Platform: any
Classifier: Programming Language :: Python :: 3
Classifier: License :: OSI Approved :: MIT License
Classifier: Operating System :: OS Independent
Requires-Python: >=3.6
Requires-Dist: numpy
Requires-Dist: sympy (>=1.0)
Provides-Extra: testing
Requires-Dist: pytest ; extra == 'testing'
Requires-Dist: pytest-cov ; extra == 'testing'
